examples/__init__.py
examples/fastapi_interview.py
examples/beautify/__init__.py
examples/beautify/nodes.py
examples/beautify/run.py
examples/book_translator/__init__.py
examples/book_translator/models.py
examples/book_translator/nodes/__init__.py
examples/book_translator/nodes/assembler.py
examples/book_translator/nodes/glossary.py
examples/book_translator/nodes/splitter.py
examples/book_translator/nodes/tools.py
examples/booking/__init__.py
examples/booking/main.py
examples/booking/run_booking.py
examples/booking/api/__init__.py
examples/booking/api/app.py
examples/booking/api/db.py
examples/booking/api/models.py
examples/booking/api/routes/__init__.py
examples/booking/nodes/__init__.py
examples/booking/nodes/schema.py
examples/booking/nodes/slots_handler.py
examples/booking/tests/__init__.py
examples/booking/tests/test_api_db.py
examples/booking/tests/test_api_models.py
examples/booking/tests/test_booking.py
examples/booking/tests/test_e2e.py
examples/booking/tests/test_fly_config.py
examples/booking/tests/test_main.py
examples/booking/tests/test_routes_appointments.py
examples/booking/tests/test_routes_calendars.py
examples/booking/tests/test_routes_chat.py
examples/booking/tests/test_routes_slots.py
examples/codegen/__init__.py
examples/codegen/models/__init__.py
examples/codegen/models/schemas.py
examples/codegen/tests/__init__.py
examples/codegen/tests/test_ai_helpers.py
examples/codegen/tests/test_ast_analysis.py
examples/codegen/tests/test_code_analysis.py
examples/codegen/tests/test_code_context.py
examples/codegen/tests/test_code_nav.py
examples/codegen/tests/test_dependency_tools.py
examples/codegen/tests/test_example_tools.py
examples/codegen/tests/test_git_tools.py
examples/codegen/tests/test_impl_agent_schemas.py
examples/codegen/tests/test_impl_agent_v4_graph.py
examples/codegen/tests/test_jedi_analysis.py
examples/codegen/tests/test_meta_tools.py
examples/codegen/tests/test_plan_discovery_prompt.py
examples/codegen/tests/test_syntax_tools.py
yamlgraph-0.4.10.dist-info/licenses/LICENSE
yamlgraph-0.4.10.dist-info/METADATA
yamlgraph-0.4.10.dist-info/WHEEL
yamlgraph-0.4.10.dist-info/entry_points.txt
yamlgraph-0.4.10.dist-info/top_level.txt
yamlgraph-0.4.10.dist-info/RECORD
