Metadata-Version: 2.4
Name: yamlgraph
Version: 0.4.10
Summary: YAML-first framework for building LLM pipelines with LangGraph
License: MIT
Requires-Python: <3.14,>=3.11
License-File: LICENSE
Requires-Dist: langchain-anthropic>=0.3.0
Requires-Dist: langchain-mistralai>=0.2.0
Requires-Dist: langchain-openai>=0.3.0
Requires-Dist: langgraph>=0.2.0
Requires-Dist: langgraph-checkpoint-sqlite>=2.0.0
Requires-Dist: pydantic>=2.0.0
Requires-Dist: python-dotenv>=1.0.0
Requires-Dist: pyyaml>=6.0
Requires-Dist: langsmith>=0.1.0
Requires-Dist: jinja2>=3.1.0
Provides-Extra: dev
Requires-Dist: pytest>=7.0.0; extra == "dev"
Requires-Dist: pytest-asyncio>=0.23.0; extra == "dev"
Requires-Dist: pytest-cov>=4.0.0; extra == "dev"
Requires-Dist: ruff>=0.1.0; extra == "dev"
Provides-Extra: analysis
Requires-Dist: jedi>=0.19.0; extra == "analysis"
Provides-Extra: websearch
Requires-Dist: ddgs>=6.0.0; extra == "websearch"
Provides-Extra: storyboard
Requires-Dist: replicate>=0.25.0; extra == "storyboard"
Provides-Extra: replicate
Requires-Dist: langchain-litellm>=0.3.0; extra == "replicate"
Provides-Extra: redis
Requires-Dist: langgraph-checkpoint-redis>=0.3.0; extra == "redis"
Provides-Extra: redis-simple
Requires-Dist: redis>=5.0.0; extra == "redis-simple"
Requires-Dist: orjson>=3.9.0; extra == "redis-simple"
Provides-Extra: rag
Requires-Dist: lancedb>=0.4.0; extra == "rag"
Requires-Dist: openai>=1.0.0; extra == "rag"
Provides-Extra: booking
Requires-Dist: fastapi>=0.110.0; extra == "booking"
Requires-Dist: httpx>=0.27.0; extra == "booking"
Requires-Dist: uvicorn>=0.27.0; extra == "booking"
Provides-Extra: npc
Requires-Dist: fastapi>=0.110.0; extra == "npc"
Requires-Dist: python-multipart>=0.0.20; extra == "npc"
Requires-Dist: uvicorn>=0.27.0; extra == "npc"
Provides-Extra: digest
Requires-Dist: feedparser>=6.0.0; extra == "digest"
Requires-Dist: resend>=2.0.0; extra == "digest"
Requires-Dist: beautifulsoup4>=4.12.0; extra == "digest"
Requires-Dist: httpx>=0.27.0; extra == "digest"
Requires-Dist: fastapi>=0.110.0; extra == "digest"
Requires-Dist: slowapi>=0.1.9; extra == "digest"
Requires-Dist: uvicorn>=0.27.0; extra == "digest"
Requires-Dist: python-multipart>=0.0.9; extra == "digest"
Dynamic: license-file
